effectpy/__init__.py
effectpy/anyio_runtime.py
effectpy/channel.py
effectpy/chunk.py
effectpy/clock.py
effectpy/context.py
effectpy/core.py
effectpy/deferred.py
effectpy/duration.py
effectpy/either.py
effectpy/exporters.py
effectpy/fiberref.py
effectpy/hub.py
effectpy/instrument.py
effectpy/layer.py
effectpy/logger.py
effectpy/metrics.py
effectpy/option.py
effectpy/pipeline.py
effectpy/queue.py
effectpy/random.py
effectpy/ref.py
effectpy/result.py
effectpy/runtime.py
effectpy/schedule.py
effectpy/scope.py
effectpy/services.py
effectpy/stream.py
effectpy/tracer.py
effectpy/validated.py
effectpy-0.2.0.dist-info/METADATA
effectpy-0.2.0.dist-info/WHEEL
effectpy-0.2.0.dist-info/RECORD
