Metadata-Version: 2.4
Name: effectpy
Version: 0.2.0
Summary: Effect/ZIO-inspired structured async for Python
Requires-Python: >=3.10
Requires-Dist: aiohttp>=3.12.15
Requires-Dist: anyio>=4.10.0
Provides-Extra: anyio
Requires-Dist: anyio>=4.0; extra == 'anyio'
Provides-Extra: docs
Requires-Dist: mkdocs-autorefs>=1.0; extra == 'docs'
Requires-Dist: mkdocs-material>=9.5; extra == 'docs'
Requires-Dist: mkdocs>=1.5; extra == 'docs'
Requires-Dist: mkdocstrings[python]>=0.24; extra == 'docs'
Provides-Extra: exporters
Requires-Dist: aiohttp>=3.8; extra == 'exporters'
